bdren_finance/__init__.py
bdren_finance-4.0.0.dist-info/licenses/LICENSE
bdren_finance-4.0.0.dist-info/METADATA
bdren_finance-4.0.0.dist-info/WHEEL
bdren_finance-4.0.0.dist-info/top_level.txt
bdren_finance-4.0.0.dist-info/RECORD
