Metadata-Version: 2.4
Name: bdren-finance
Version: 4.0.0
Summary: A comprehensive Python package for interacting with the BdREN Finance API
Home-page: https://github.com/shuvoooo/bdren_finance_api_package
Author: Shuvo
Author-email: Shuvo <shuvo.punam@gmail.com>
License: MIT
Project-URL: Homepage, https://github.com/shuvoooo/bdren_finance_api_package
Project-URL: Documentation, https://github.com/shuvoooo/bdren_finance_api_package#readme
Project-URL: Repository, https://github.com/shuvoooo/bdren_finance_api_package
Project-URL: Issues, https://github.com/shuvoooo/bdren_finance_api_package/issues
Keywords: bdren,finance,api,django,accounting,financial
Classifier: Development Status :: 5 - Production/Stable
Classifier: Intended Audience :: Developers
Classifier: Topic :: Software Development :: Libraries :: Python Modules
Classifier: Topic :: Office/Business :: Financial
Classifier: License :: OSI Approved :: MIT License
Classifier: Programming Language :: Python :: 3
Classifier: Programming Language :: Python :: 3.6
Classifier: Programming Language :: Python :: 3.7
Classifier: Programming Language :: Python :: 3.8
Classifier: Programming Language :: Python :: 3.9
Classifier: Programming Language :: Python :: 3.10
Classifier: Programming Language :: Python :: 3.11
Classifier: Programming Language :: Python :: 3.12
Classifier: Operating System :: OS Independent
Classifier: Framework :: Django
Requires-Python: >=3.6
License-File: LICENSE
Requires-Dist: requests>=2.20.0
Requires-Dist: urllib3>=1.24.0
Requires-Dist: Django>=2.0
Dynamic: author
Dynamic: home-page
Dynamic: license-file
Dynamic: requires-python
